LICENSE
MANIFEST.in
setup.py
muv/__init__.py
muv/modal.py
muv/muv.py
muv/util.py
muv/version.py
muv.egg-info/PKG-INFO
muv.egg-info/SOURCES.txt
muv.egg-info/dependency_links.txt
muv.egg-info/entry_points.txt
muv.egg-info/requires.txt
muv.egg-info/top_level.txt
muv/conf/muv.conf
muv/conf/palette.json
muv/conf/palette_without_italics.json